{
  "appPageId" : "cca84e1c-cacb-417e-83d4-cde945b655a7",
  "componentName" : "community_layout:sldsFlexibleLayout",
  "dataProviders" : [ ],
  "id" : "ab93a978-f63b-473c-8060-a30eb0fd871f",
  "label" : "Checkout",
  "regions" : [ {
    "components" : [ {
      "componentAttributes" : {
        "backgroundImageConfig" : "",
        "backgroundImageOverlay" : "rgba(0,0,0,0)",
        "sectionConfig" : "{\"UUID\":\"722e19ac-6e8c-4df2-9ba8-fde06d4e2ff0\",\"columns\":[{\"UUID\":\"1a43b7f6-e469-46b3-a2b6-4062c3ab5f4d\",\"columnName\":\"Column 1\",\"columnKey\":\"col1\",\"columnWidth\":\"8\",\"seedComponents\":[]},{\"UUID\":\"98ac21c9-fcf9-40c1-a85f-9328cf0476ed\",\"columnName\":\"Column 2\",\"columnKey\":\"col2\",\"columnWidth\":\"4\",\"seedComponents\":[]}]}"
      },
      "componentName" : "community_layout:section",
      "id" : "722e19ac-6e8c-4df2-9ba8-fde06d4e2ff0",
      "regions" : [ {
        "components" : [ {
          "componentAttributes" : {
            "stepsConfig" : "[{\"checkoutStepKey\":\"ShippingAddress\",\"checkoutStepName\":\"Shipping Address\",\"proceedButtonLabel\":\"Next\",\"isExpanded\":true,\"seedComponents\":[{\"fqn\":\"commerce_unified_checkout:shipping\",\"attributes\":null}]},{\"checkoutStepKey\":\"ShippingMethod\",\"checkoutStepName\":\"Shipping Method\",\"proceedButtonLabel\":\"Next\",\"isExpanded\":true,\"seedComponents\":[{\"fqn\":\"commerce_unified_checkout:shippingMethod\",\"attributes\":null}]},{\"checkoutStepKey\":\"Payment\",\"checkoutStepName\":\"Payment\",\"proceedButtonLabel\":\"Place Order\",\"isExpanded\":true,\"seedComponents\":[{\"fqn\":\"commerce_unified_checkout:multiPaymentAccordion\",\"attributes\":null}]}]"
          },
          "componentName" : "commerce_unified_checkout:checkout",
          "id" : "3181ffa6-61a9-4455-92b1-01f0cc73d05f",
          "regions" : [ {
            "components" : [ {
              "componentAttributes" : {
                "backToListLabel" : "Back to list",
                "componentHeaderEditAddressLabel" : "Edit Address",
                "editAddressLabel" : "Edit",
                "makeDefaultAddressLabel" : "Make this my default address",
                "newAddressButtonLabel" : "New Address",
                "phoneNumberLabel" : "Phone Number",
                "phoneNumberPlaceholderText" : "",
                "shippingAddressLimit" : "6",
                "shippingAddressLimitIncrease" : "6",
                "showMoreButtonLabel" : "Show More",
                "summaryModeEnabled" : true
              },
              "componentName" : "commerce_unified_checkout:shipping",
              "id" : "6d735463-506a-4185-ab7e-c06cd1114b0a",
              "renderPriority" : "NEUTRAL",
              "renditionMap" : { },
              "type" : "component"
            } ],
            "id" : "5672b084-8bb5-42aa-b121-abd77ed88d91",
            "regionLabel" : "Shipping Address",
            "regionName" : "ShippingAddress",
            "renditionMap" : { },
            "type" : "region"
          }, {
            "components" : [ {
              "componentAttributes" : { },
              "componentName" : "commerce_unified_checkout:shippingMethod",
              "id" : "a94c3861-a47d-4fad-a4b5-24a2e072ddb5",
              "renderPriority" : "NEUTRAL",
              "renditionMap" : { },
              "type" : "component"
            } ],
            "id" : "fcc3768a-5c35-4069-bf52-5011b3318798",
            "regionLabel" : "Shipping Method",
            "regionName" : "ShippingMethod",
            "renditionMap" : { },
            "type" : "region"
          }, {
            "components" : [ {
              "componentAttributes" : {
                "billingAddressFieldsetLegendLabel" : "Billing Address",
                "billingAddressSameAsShippingAddressLabel" : "Same as shipping address",
                "cardPaymentLabel" : "Credit Card",
                "headerLabel" : "Purchase Order",
                "inputLabel" : "Purchase Order Number",
                "placeholderLabel" : "",
                "requireBillingAddress" : true,
                "showBillingAddressHeading" : true
              },
              "componentName" : "commerce_unified_checkout:multiPaymentAccordion",
              "id" : "42b7b72c-c395-4aa1-9fd6-010db44d7f90",
              "renderPriority" : "NEUTRAL",
              "renditionMap" : { },
              "type" : "component"
            } ],
            "id" : "37bdad27-3558-4542-83c2-72c440f87895",
            "regionLabel" : "Payment",
            "regionName" : "Payment",
            "renditionMap" : { },
            "type" : "region"
          } ],
          "renderPriority" : "NEUTRAL",
          "renditionMap" : { },
          "type" : "component"
        } ],
        "id" : "1a43b7f6-e469-46b3-a2b6-4062c3ab5f4d",
        "regionLabel" : "Column 1",
        "regionName" : "col1",
        "renditionMap" : { },
        "type" : "region"
      }, {
        "components" : [ {
          "componentAttributes" : {
            "discountAmountTextSize" : "small",
            "originalTextColor" : "rgb(116, 116, 116)",
            "originalTextSize" : "small",
            "shippingTextSize" : "small",
            "showDiscountAmount" : true,
            "showOriginalPrice" : true,
            "showShippingPrice" : true,
            "showSubtotalPrice" : true,
            "showTaxIncludedLabel" : false,
            "showTaxPrice" : true,
            "subtotalTextSize" : "small",
            "taxTextSize" : "small",
            "totalTextSize" : "medium"
          },
          "componentName" : "commerce_builder:cartSummary",
          "id" : "58c07486-b6b2-467e-9429-5f3a9015f742",
          "regions" : [ {
            "components" : [ {
              "componentAttributes" : {
                "backgroundColor" : "",
                "paddingHorizontal" : "none",
                "paddingVertical" : "none",
                "text" : "Summary",
                "textAlign" : "left",
                "textDecoration" : "{\"bold\": true}",
                "textDisplayInfo" : "{\"headingTag\": \"h2\", \"textStyle\": \"heading-medium\"}"
              },
              "componentName" : "dxp_base:textBlock",
              "id" : "a61167df-26a8-4220-91ff-71cfdf03bdf3",
              "renderPriority" : "NEUTRAL",
              "renditionMap" : { },
              "type" : "component"
            } ],
            "id" : "87adfdb9-1aca-4baf-a5ff-7974300bda63",
            "regionName" : "headerText",
            "type" : "region"
          }, {
            "components" : [ {
              "componentAttributes" : {
                "backgroundColor" : "",
                "paddingHorizontal" : "none",
                "paddingVertical" : "none",
                "text" : "Promotions",
                "textAlign" : "left",
                "textDecoration" : "{}",
                "textDisplayInfo" : "{\"headingTag\": \"p\", \"textStyle\": \"body-regular\"}"
              },
              "componentName" : "dxp_base:textBlock",
              "id" : "87a675a0-493a-4c85-94e8-a29631f78eaa",
              "renderPriority" : "NEUTRAL",
              "renditionMap" : { },
              "type" : "component"
            } ],
            "id" : "6c13b331-d2c9-41d2-aba3-4bd2718b7404",
            "regionName" : "promotionsLabel",
            "type" : "region"
          }, {
            "components" : [ {
              "componentAttributes" : {
                "backgroundColor" : "",
                "paddingHorizontal" : "none",
                "paddingVertical" : "none",
                "text" : "Shipping",
                "textAlign" : "left",
                "textDecoration" : "{}",
                "textDisplayInfo" : "{\"headingTag\": \"p\", \"textStyle\": \"body-regular\"}"
              },
              "componentName" : "dxp_base:textBlock",
              "id" : "5d2e2c49-4d58-433f-aaea-e5f71bbb4521",
              "renderPriority" : "NEUTRAL",
              "renditionMap" : { },
              "type" : "component"
            } ],
            "id" : "2dfb45f5-d95b-4c39-b537-d48843281bf7",
            "regionName" : "shippingLabel",
            "type" : "region"
          }, {
            "components" : [ {
              "componentAttributes" : {
                "backgroundColor" : "",
                "paddingHorizontal" : "none",
                "paddingVertical" : "none",
                "text" : "Subtotal",
                "textAlign" : "left",
                "textDecoration" : "{}",
                "textDisplayInfo" : "{\"headingTag\": \"p\", \"textStyle\": \"body-regular\"}"
              },
              "componentName" : "dxp_base:textBlock",
              "id" : "2fb9b5fe-44a6-4a30-b646-5f0006fbca03",
              "renderPriority" : "NEUTRAL",
              "renditionMap" : { },
              "type" : "component"
            } ],
            "id" : "441ef258-67d9-4b2a-9573-c96dc02a8f47",
            "regionName" : "subtotalLabel",
            "type" : "region"
          }, {
            "components" : [ {
              "componentAttributes" : {
                "backgroundColor" : "",
                "paddingHorizontal" : "none",
                "paddingVertical" : "none",
                "text" : "Tax included",
                "textAlign" : "right",
                "textDecoration" : "{}",
                "textDisplayInfo" : "{\"headingTag\": \"p\", \"textStyle\": \"body-regular\"}"
              },
              "componentName" : "dxp_base:textBlock",
              "id" : "7eae411d-2dee-4806-b897-6a1b00b7db28",
              "renderPriority" : "NEUTRAL",
              "renditionMap" : { },
              "type" : "component"
            } ],
            "id" : "6f88f64c-58e0-4ef8-aa8b-0bc3125ccf13",
            "regionName" : "taxIncludedLabel",
            "type" : "region"
          }, {
            "components" : [ {
              "componentAttributes" : {
                "backgroundColor" : "",
                "paddingHorizontal" : "none",
                "paddingVertical" : "none",
                "text" : "Tax",
                "textAlign" : "left",
                "textDecoration" : "{}",
                "textDisplayInfo" : "{\"headingTag\": \"p\", \"textStyle\": \"body-regular\"}"
              },
              "componentName" : "dxp_base:textBlock",
              "id" : "e7adc3f1-8c96-40da-9d51-dc50d1798aa7",
              "renderPriority" : "NEUTRAL",
              "renditionMap" : { },
              "type" : "component"
            } ],
            "id" : "dd884f65-15d7-4e0a-a4ba-645e1ccaa303",
            "regionName" : "taxLabel",
            "type" : "region"
          }, {
            "components" : [ {
              "componentAttributes" : {
                "backgroundColor" : "",
                "paddingHorizontal" : "none",
                "paddingVertical" : "none",
                "text" : "Total",
                "textAlign" : "left",
                "textDecoration" : "{\"bold\": true}",
                "textDisplayInfo" : "{\"headingTag\": \"p\", \"textStyle\": \"heading-small\"}"
              },
              "componentName" : "dxp_base:textBlock",
              "id" : "293f510d-7fe6-4cc0-8cf6-9c79780740b0",
              "renderPriority" : "NEUTRAL",
              "renditionMap" : { },
              "type" : "component"
            } ],
            "id" : "9a20b55b-be5a-4712-b1ea-86ff0b9ab483",
            "regionName" : "totalLabel",
            "type" : "region"
          } ],
          "renderPriority" : "NEUTRAL",
          "renditionMap" : { },
          "type" : "component"
        } ],
        "id" : "98ac21c9-fcf9-40c1-a85f-9328cf0476ed",
        "regionLabel" : "Column 2",
        "regionName" : "col2",
        "renditionMap" : { },
        "type" : "region"
      } ],
      "renderPriority" : "NEUTRAL",
      "renditionMap" : { },
      "scopedBrandingSetId" : null,
      "type" : "component"
    } ],
    "id" : "b7c8cdd5-ca8d-415c-bbeb-0b16c76678dd",
    "regionName" : "content",
    "type" : "region"
  } ],
  "themeLayoutType" : "Checkout",
  "type" : "view",
  "viewType" : "current-checkout"
}