{
    "CustomJavaScript": "{}",
    "ElementTypeComponentMapping": "{\"ElementTypeToHTMLTemplateList\":[]}",
    "IsIntegrationProcedure": true,
    "IsMetadataCacheDisabled": false,
    "IsOmniScriptEmbeddable": false,
    "IsTestProcedure": false,
    "IsWebCompEnabled": false,
    "Language": "Procedure",
    "Name": "Team Get Account Details",
    "OmniProcessElement": [
        "team_getAccountDetails_Element_SetValues.json",
        "team_getAccountDetails_Element_ResponseAction.json"
    ],
    "OmniProcessKey": "team_getAccountDetails",
    "OmniProcessType": "Integration Procedure",
    "PropertySetConfig": "team_getAccountDetails_PropertySetConfig.json",
    "SubType": "getAccountDetails",
    "Type": "team",
    "UniqueName": "team_getAccountDetails_Procedure_6",
    "VlocityDataPackType": "SObject",
    "VlocityRecordSObjectType": "OmniProcess",
    "VlocityRecordSourceKey": "OmniProcess/team/getAccountDetails/Procedure",
    "WebComponentKey": "97c35ffd-7bae-8b5c-87f5-c96d55aee656"
}